<?xml version="1.0" encoding="UTF-8"?>
<node>
<version>6</version>
<dict>
  <key>title</key><string>The OSI Model</string>
  <key>nodeid</key><string>a13b4642-8e92-4ddd-8f8b-5f7429c2ecc0</string>
  <key>modified_time</key><integer>1586877327</integer>
  <key>version</key><integer>6</integer>
  <key>content_type</key><string>text/xhtml+xml</string>
  <key>created_time</key><integer>1586877149</integer>
  <key>info_sort_dir</key><integer>1</integer>
  <key>order</key><integer>4</integer>
  <key>info_sort</key><string>order</string>
</dict>
</node>
